click_complete_fig/__init__.py
click_complete_fig/fig.py
click_complete_fig-1.1.1.dist-info/LICENSE
click_complete_fig-1.1.1.dist-info/METADATA
click_complete_fig-1.1.1.dist-info/WHEEL
click_complete_fig-1.1.1.dist-info/top_level.txt
click_complete_fig-1.1.1.dist-info/RECORD
