Metadata-Version: 2.1
Name: click-complete-fig
Version: 1.1.1
Summary: Autogenerate Completions for CLI tools built with click
Home-page: https://github.com/withfig/autocomplete-tools
Author: Fig
Author-email: hello@fig.io
License: MIT
Project-URL: Bug Tracker, https://github.com/withfig/autocomplete-tools/issues
Keywords: click,cli,completions,framework,terminal,fig
Classifier: Programming Language :: Python :: 3
Classifier: License :: OSI Approved :: MIT License
Classifier: Operating System :: OS Independent
Requires-Python: >=3.6
License-File: LICENSE
Requires-Dist: click
